vardelta/Delta.py
vardelta/__init__.py
vardelta-1.4.dist-info/LICENSE
vardelta-1.4.dist-info/METADATA
vardelta-1.4.dist-info/WHEEL
vardelta-1.4.dist-info/top_level.txt
vardelta-1.4.dist-info/RECORD
