Metadata-Version: 2.1
Name: vardelta
Version: 1.4
Summary: A package used to track the history of a variable.
Author-email: Jacob Zufall <jacobzufall@gmail.com>
Project-URL: Homepage, https://github.com/JacobZufall/vardelta
Project-URL: Issues, https://github.com/JacobZufall/vardelta/issues
Classifier: Programming Language :: Python :: 3
Classifier: License :: OSI Approved :: GNU General Public License v2 (GPLv2)
Classifier: Operating System :: OS Independent
Requires-Python: >3.11
License-File: LICENSE
